odoo/addons/account_invoice_clearing/README.rst
odoo/addons/account_invoice_clearing/__init__.py
odoo/addons/account_invoice_clearing/__manifest__.py
odoo/addons/account_invoice_clearing/i18n/account_invoice_clearing.pot
odoo/addons/account_invoice_clearing/i18n/es.po
odoo/addons/account_invoice_clearing/i18n/it.po
odoo/addons/account_invoice_clearing/models/__init__.py
odoo/addons/account_invoice_clearing/models/account_move.py
odoo/addons/account_invoice_clearing/readme/CONTRIBUTORS.rst
odoo/addons/account_invoice_clearing/readme/CREDITS.rst
odoo/addons/account_invoice_clearing/readme/DESCRIPTION.rst
odoo/addons/account_invoice_clearing/readme/ROADMAP.rst
odoo/addons/account_invoice_clearing/readme/USAGE.rst
odoo/addons/account_invoice_clearing/security/ir.model.access.csv
odoo/addons/account_invoice_clearing/static/description/icon.png
odoo/addons/account_invoice_clearing/static/description/index.html
odoo/addons/account_invoice_clearing/tests/__init__.py
odoo/addons/account_invoice_clearing/tests/test_clearing_wizard.py
odoo/addons/account_invoice_clearing/views/account_move_view.xml
odoo/addons/account_invoice_clearing/wizards/__init__.py
odoo/addons/account_invoice_clearing/wizards/account_invoice_clearing_wizard.py
odoo/addons/account_invoice_clearing/wizards/account_invoice_clearing_wizard_views.xml
odoo_addon_account_invoice_clearing-16.0.1.0.1.4.dist-info/METADATA
odoo_addon_account_invoice_clearing-16.0.1.0.1.4.dist-info/WHEEL
odoo_addon_account_invoice_clearing-16.0.1.0.1.4.dist-info/top_level.txt
odoo_addon_account_invoice_clearing-16.0.1.0.1.4.dist-info/RECORD
